{
  "metadata": {
    "realm": null,
    "entityType": "sunIdentityRepositoryService",
    "entityId": "default/group",
    "uid": "ou=group,ou=default,ou=GlobalConfig,ou=1.0,ou=sunIdentityRepositoryService,ou=services,dc=amconfig",
    "sunServiceID": "SupportedIdentities",
    "objectClass": [
      "top",
      "sunServiceComponent"
    ],
    "pathParams": {},
    "ou": null
  },
  "data": {
    "_id": "default/group",
    "_type": {
      "_id": "sunIdentityRepositoryService",
      "name": "sunIdentityRepositoryService",
      "collection": false
    },
    "canHaveMembers": [
      "user"
    ],
    "canAddMembers": [
      "user"
    ]
  }
}